README.rst
setup.py
backward/__init__.py
backward/decorators.py
backward/helpers.py
backward/middleware.py
backward/models.py
backward/settings.py
backward/urls.py
backward/utils.py
backward/views.py
backward/backends/__init__.py
backward/backends/base.py
backward/backends/cookie.py
backward/backends/session.py
backward/tests/__init__.py
backward/tests/models.py
backward/tests/settings.py
backward/tests/tests.py
backward/tests/urls.py
backward/tests/views.py
django_backward.egg-info/PKG-INFO
django_backward.egg-info/SOURCES.txt
django_backward.egg-info/dependency_links.txt
django_backward.egg-info/not-zip-safe
django_backward.egg-info/pbr.json
django_backward.egg-info/top_level.txt