Metadata-Version: 1.1
Name: django-backward
Version: 0.3.6
Summary: A Django application to store your previous history and action in your session engine
Home-page: http://github.com/thoas/django-backward
Author: Florent Messa
Author-email: florent.messa@gmail.com
License: UNKNOWN
Platform: UNKNOWN
Classifier: Environment :: Web Environment
Classifier: Intended Audience :: Developers
Classifier: License :: OSI Approved :: MIT License
Classifier: Operating System :: OS Independent
Classifier: Programming Language :: Python
Classifier: Programming Language :: Python :: 3
Classifier: Topic :: Utilities
